snapfs/__init__.py
snapfs/cli.py
snapfs/client.py
snapfs/config.py
snapfs/gateway.py
snapfs/scanner.py
snapfs-0.1.0.dist-info/LICENSE
snapfs-0.1.0.dist-info/METADATA
snapfs-0.1.0.dist-info/WHEEL
snapfs-0.1.0.dist-info/entry_points.txt
snapfs-0.1.0.dist-info/top_level.txt
snapfs-0.1.0.dist-info/RECORD
