Metadata-Version: 2.1
Name: snapfs
Version: 0.1.0
Summary: SnapFS Python client and CLI
Author-email: Ryan Galloway <ryan@rsg.io>
License: Apache License
Project-URL: Homepage, https://github.com/snapfsio/snapfs
Project-URL: Source, https://github.com/snapfsio/snapfs
Project-URL: Issues, https://github.com/snapfsio/snapfs/issues
Classifier: Programming Language :: Python :: 3
Classifier: Programming Language :: Python :: 3 :: Only
Classifier: License :: OSI Approved :: Apache Software License
Classifier: Operating System :: OS Independent
Requires-Python: >=3.8
License-File: LICENSE
Requires-Dist: aiohttp>=3.8
Requires-Dist: click>=8.0
Requires-Dist: rich>=13.0
